MANIFEST.in
README.md
requirements.txt
setup.cfg
setup.py
src/cassandras3/__init__.py
src/cassandras3/log.py
src/cassandras3/main.py
src/cassandras3.egg-info/PKG-INFO
src/cassandras3.egg-info/SOURCES.txt
src/cassandras3.egg-info/dependency_links.txt
src/cassandras3.egg-info/entry_points.txt
src/cassandras3.egg-info/requires.txt
src/cassandras3.egg-info/top_level.txt
src/cassandras3.egg-info/zip-safe
src/cassandras3/aws/__init__.py
src/cassandras3/aws/clients.py
src/cassandras3/cli/__init__.py
src/cassandras3/cli/backup.py
src/cassandras3/cli/restore.py
src/cassandras3/cli/view.py
src/cassandras3/util/__init__.py
src/cassandras3/util/nodetool.py
src/test/aws/__init__.py
src/test/aws/test_clients.py
src/test/cli/__init__.py
src/test/cli/test_backup.py
src/test/cli/test_restore.py
src/test/cli/test_view.py
src/test/util/__init__.py
src/test/util/test_nodetool.py