Metadata-Version: 1.0
Name: cassandras3
Version: 0.1.6
Summary: Cassandra S3 Backup, View and Restore
Home-page: https://github.com/deviavir/cassandras3
Author: Chase Sillevis
Author-email: chase@sillevis.net
License: MIT
Platform: UNKNOWN
